LICENSE
README.md
setup.cfg
setup.py
tests/test_weather.py
weather_forecast_server/__init__.py
weather_forecast_server/__main__.py
weather_forecast_server/server.py
weather_forecast_server/weather.py
weather_forecast_server.egg-info/PKG-INFO
weather_forecast_server.egg-info/SOURCES.txt
weather_forecast_server.egg-info/dependency_links.txt
weather_forecast_server.egg-info/entry_points.txt
weather_forecast_server.egg-info/not-zip-safe
weather_forecast_server.egg-info/requires.txt
weather_forecast_server.egg-info/top_level.txt