Metadata-Version: 2.4
Name: weather-forecast-server
Version: 0.0.7
Summary: weather-forecast-server: MCP server for weather forecast
Home-page: https://github.com/shibing624/weather-forecast-server
Author: XuMing
Author-email: xuming624@qq.com
License: Apache License 2.0
Keywords: weather_forecast_server,weather forecast,server,weather,forecast
Classifier: Intended Audience :: Developers
Classifier: Operating System :: OS Independent
Classifier: Natural Language :: Chinese (Simplified)
Classifier: Natural Language :: Chinese (Traditional)
Classifier: Programming Language :: Python
Classifier: Programming Language :: Python :: 3
Classifier: Topic :: Text Processing
Classifier: Topic :: Text Processing :: Indexing
Classifier: Topic :: Text Processing :: Linguistic
Requires-Python: >=3.10
License-File: LICENSE
Requires-Dist: mcp
Requires-Dist: requests
Requires-Dist: loguru
Dynamic: author
Dynamic: author-email
Dynamic: classifier
Dynamic: description
Dynamic: description-content-type
Dynamic: home-page
Dynamic: keywords
Dynamic: license
Dynamic: license-file
Dynamic: requires-dist
Dynamic: requires-python
Dynamic: summary
